DRL_Snakey/__init__.py
DRL_Snakey/agent/A*.py
DRL_Snakey/agent/DP_AI.py
DRL_Snakey/agent/Logic_AI.py
DRL_Snakey/agent/MC_AI.py
DRL_Snakey/agent/Stupid_AI.py
DRL_Snakey/agent/TD_AI.py
DRL_Snakey/agent/__init__.py
DRL_Snakey/core/UI.py
DRL_Snakey/core/__init__.py
DRL_Snakey/core/game.py
DRL_Snakey/core/snake.py
DRL_Snakey/images/Pineapple.png
DRL_Snakey/images/bm.png
DRL_Snakey/images/dead_snake.png
DRL_Snakey/images/game_start.png
DRL_Snakey/images/snake.png
DRL_Snakey/utils/__init__.py
DRL_Snakey/utils/directions.py
DRL_Snakey/utils/functions.py
DRL_Snakey/utils/training.py
DRL_Snakey-1.2.dist-info/LICENSE
DRL_Snakey-1.2.dist-info/METADATA
DRL_Snakey-1.2.dist-info/WHEEL
DRL_Snakey-1.2.dist-info/top_level.txt
DRL_Snakey-1.2.dist-info/zip-safe
DRL_Snakey-1.2.dist-info/RECORD
