Metadata-Version: 2.1
Name: DRL-Snakey
Version: 1.2
Summary: A Deep Reinforcement Learning study package. With game environment.
Home-page: https://github.com/cstrikest/DRL_Snakey
Author: YANG Xuezhi
Author-email: cstrikest@gmail.com
License: GPL
Platform: UNKNOWN
Classifier: Programming Language :: Python :: 3.6
Classifier: Environment :: MacOS X
Classifier: License :: OSI Approved :: GNU General Public License v3 (GPLv3)
Classifier: Natural Language :: Chinese (Simplified)
Classifier: Topic :: Scientific/Engineering :: Artificial Intelligence
Requires-Dist: numpy
Requires-Dist: tensorflow
Requires-Dist: h5py
Requires-Dist: pygame
Requires-Dist: matplotlib
